CHANGELOG.txt
MANIFEST.in
README.md
setup.py
pidi_display_tk/__init__.py
pidi_display_tk.egg-info/PKG-INFO
pidi_display_tk.egg-info/SOURCES.txt
pidi_display_tk.egg-info/dependency_links.txt
pidi_display_tk.egg-info/entry_points.txt
pidi_display_tk.egg-info/requires.txt
pidi_display_tk.egg-info/top_level.txt