Metadata-Version: 2.1
Name: pidi-display-tk
Version: 0.0.2
Summary: pidi plugin to display output using PIL and Tk.
Home-page: https://github.com/pimoroni/pidi-plugins
Author: Philip Howard
Author-email: phil@pimoroni.com
License: MIT
Platform: UNKNOWN
Classifier: Environment :: X11 Applications
Classifier: License :: OSI Approved :: MIT License
Classifier: Operating System :: POSIX :: Linux
Classifier: Programming Language :: Python :: 3.6
Requires-Python: >=2.7
